iso10383/__init__.py
iso10383/_data
iso10383/_iso10383.py
iso10383/py.typed
iso10383-2024.12.9.dist-info/LICENSE
iso10383-2024.12.9.dist-info/METADATA
iso10383-2024.12.9.dist-info/WHEEL
iso10383-2024.12.9.dist-info/top_level.txt
iso10383-2024.12.9.dist-info/RECORD
