Metadata-Version: 2.1
Name: iso10383
Version: 2024.12.9
Summary: A Python wrapper around the data provided by the ISO 10383 specification.
Author-email: Tanner Corcoran <tannerbcorcoran@gmail.com>
Maintainer-email: Tanner Corcoran <tannerbcorcoran@gmail.com>
License: Apache 2.0
Project-URL: Homepage, https://github.com/tanrbobanr/iso10383
Project-URL: Documentation, https://github.com/tanrbobanr/iso10383/blob/main/README.md
Project-URL: Changelog, https://github.com/tanrbobanr/iso10383/blob/main/CHANGELOG.md
Project-URL: License, https://github.com/tanrbobanr/iso10383/blob/main/LICENSE
Project-URL: Source, https://github.com/tanrbobanr/iso10383
Project-URL: Bug Tracker, https://github.com/tanrbobanr/iso10383/issues
Keywords: iso10383,iso 10383,iso-10383,iso,market identifier codes,mics
Classifier: Development Status :: 4 - Beta
Classifier: Operating System :: OS Independent
Classifier: Programming Language :: Python
Classifier: Programming Language :: Python :: 3
Classifier: Programming Language :: Python :: 3 :: Only
Classifier: Programming Language :: Python :: 3.9
Classifier: Programming Language :: Python :: 3.10
Classifier: Programming Language :: Python :: 3.11
Classifier: Programming Language :: Python :: 3.12
Classifier: Programming Language :: Python :: 3.13
Classifier: Programming Language :: Python :: 3.14
Classifier: Topic :: Software Development
Classifier: Topic :: Software Development :: Libraries
Classifier: Typing :: Typed
Classifier: Topic :: Utilities
Classifier: Intended Audience :: Developers
Classifier: License :: OSI Approved :: Apache Software License
Requires-Python: >=3.9
License-File: LICENSE
Requires-Dist: typing_extensions>=4.0.0; python_version < "3.11"
